mqtt_service/__init__.py
mqtt_service/cli.py
mqtt_service/mqtt_base_device.py
mqtt_service/mqtt_base_listener.py
mqtt_service/mqtt_multi_topic_listener.py
mqtt_service/mqtt_service.py
mqtt_service/mqtt_topic_schema.py
mqtt_service-0.2.5.dist-info/AUTHORS.rst
mqtt_service-0.2.5.dist-info/LICENSE
mqtt_service-0.2.5.dist-info/METADATA
mqtt_service-0.2.5.dist-info/WHEEL
mqtt_service-0.2.5.dist-info/entry_points.txt
mqtt_service-0.2.5.dist-info/top_level.txt
mqtt_service-0.2.5.dist-info/RECORD
