Metadata-Version: 1.1
Name: mqtt_service
Version: 0.2.5
Summary: Basic framework for creating MQTT services
Home-page: https://github.com/weijia/mqtt-service
Author: Wang Richard
Author-email: wangweijia2000@sina.com
License: MIT license
Keywords: mqtt_service
Platform: UNKNOWN
Classifier: Development Status :: 2 - Pre-Alpha
Classifier: Intended Audience :: Developers
Classifier: License :: OSI Approved :: MIT License
Classifier: Natural Language :: English
Classifier: Programming Language :: Python :: 2
Classifier: Programming Language :: Python :: 2.7
Classifier: Programming Language :: Python :: 3
Classifier: Programming Language :: Python :: 3.4
Classifier: Programming Language :: Python :: 3.5
Classifier: Programming Language :: Python :: 3.6
Classifier: Programming Language :: Python :: 3.7
